{
  "name": "Yang Ren",
  "page_title": "Yang Ren 楊任 [Zhang Lu] – Romance of the Three Kingdoms Encyclopedia – Kongming’s Archives",
  "url": "https://kongming.net/encyclopedia/Yang-Ren",
  "faction": "other",
  "courtesy_name": "",
  "life_span": "AD 001–202",
  "birthplace": "",
  "chinese_name": "",
  "affiliations": [],
  "family": [],
  "ranks": [],
  "historical_notes": "",
  "novel_notes": "",
  "quotes": [],
  "sections": {
    "novel": "",
    "yang-ren": "",
    "short-biography": "Fought well against Cao Cao’s forces at Yangping, lured out and killed in battle.",
    "details": "Traditional Chinese \n\t楊任\n\n\n\t Simplified Chinese \n\t杨任\n\n\n\t Wade-Giles \n\tYang Jên\n\n\t Other Names \n\tYan Ren\n\n\t Name Notes \n\tHe is called Yan Ren in the online version of the novel and possibly in other sources.",
    "literary-appearances": "Romance of the Three Kingdoms: 67Sanguozhi: Wei 1"
  },
  "full_text": "Yang Ren 楊任\nARomance of the Three KingdomsEncyclopedia officer profile.\nYang Ren (楊任). Fought well against Cao Cao’s forces at Yangping, lured out and killed in battle. Yang Ren was affiliated with Zhang Lu. Yang Ren lived during the Later Han Dynasty periods of Chinese history.\nReturn to theThree Kingdoms Encyclopediaor browse theEncyclopedia Directory.\nReturn toThree Kingdoms Encyclopedia\nSearch\nViewAlphabeticallyA–BCDE–FGHJ–KLMN–RSTWXYZor By Kingdom- Wei- Shu- Wu- Han- JinCustom Searches- Other- Popular- Fictional- Non-Fictional- Novel Characters- Non-Novel Officers- Non-Novel Historic- Miscellaneous- Historical- Mystics- WomenKingdoms/Factions- Dong Zhuo- Gongsun Du- Gongsun Yuan- Gongsun Zan- Guo Si- Han Fu- Han Sui- Han Xuan- Kong Rong- Li Jue- Liu Biao- Liu Yao (Yong)- Liu Yu- Liu Zhang- Lü Bu- Ma Chao- Ma Teng- Shi Xie- Tao Qian- Tribe: Qiang- Tribe: Nanman- Tribe: Wuhuan- Tribe: Xianbei- Tribe: Xiongnu- Yellow Scarves- Yuan Shang- Yuan Shao- Yuan Shu- Yuan Tan- Zhang Lu- Zhang Yang- Zhang Xiu- Zhao Fan- Zhuge DanforSearch\n“Search” to browse selected faction. Search terms optional.\nSearchthroughover three-thousandofficers using the tools above.\nYang Ren楊任\nLivedAD?–215\nAffiliations\nZhang Lu\nShort Biography\nFought well against Cao Cao’s forces at Yangping, lured out and killed in battle.\nDetails\nTraditional Chinese楊任\nSimplified Chinese杨任\nWade-GilesYang Jên\nOther NamesYan Ren\nName NotesHe is called Yan Ren in the online version of the novel and possibly in other sources.\nLiterary Appearances\nRomance of the Three Kingdoms:67\nSanguozhi: Wei 1",
  "crawled_at": "2026-03-18T10:05:07.336Z",
  "char_count": 1571
}