{
  "name": "Ze Rong",
  "page_title": "Ze Rong 笮融 [Tao Qian, Zhao Yu, Xue Li, Liu Yao] – Romance of the Three Kingdoms Encyclopedia – Kongming’s Archives",
  "url": "https://kongming.net/encyclopedia/Ze-Rong",
  "faction": "other",
  "courtesy_name": "",
  "life_span": "AD 001–202",
  "birthplace": "",
  "chinese_name": "",
  "affiliations": [],
  "family": [],
  "ranks": [
    "Chancellor of Xiapi"
  ],
  "historical_notes": "",
  "novel_notes": "",
  "quotes": [],
  "sections": {
    "novel": "",
    "ze-rong": "",
    "short-biography": "Buddhist, fought against Sun Ce, had a record of betrayal and murder.",
    "details": "Traditional Chinese \n\t笮融\n\n\n\t Simplified Chinese \n\t笮融\n\n\n\t Wade-Giles \n\tTsê Jung\n\n\t Birthplace \n\tDanyang\n\n\t Other Names \n\tZhai Rong\n\n\t Name Notes \n\tAlso referred to as Zhai Rong in Generals of the South. As well as To Establish Peace.",
    "ranks": "Chancellor of Xiapi",
    "literary-appearances": "Romance of the Three Kingdoms: 15",
    "premium-external-linkage": "Ze Rong’s biography Within Liu Yao’s SGZ"
  },
  "full_text": "Ze Rong 笮融\nARomance of the Three KingdomsEncyclopedia officer profile.\nZe Rong (笮融)was born in Danyang. Buddhist, fought against Sun Ce, had a record of betrayal and murder. Ze Rong was affiliated with Tao Qian, Zhao Yu, Xue Li, and Liu Yao. Ze Rong lived during the Later Han Dynasty periods of Chinese history.\nReturn to theThree Kingdoms Encyclopediaor browse theEncyclopedia Directory.\nReturn toThree Kingdoms Encyclopedia\nSearch\nViewAlphabeticallyA–BCDE–FGHJ–KLMN–RSTWXYZor By Kingdom- Wei- Shu- Wu- Han- JinCustom Searches- Other- Popular- Fictional- Non-Fictional- Novel Characters- Non-Novel Officers- Non-Novel Historic- Miscellaneous- Historical- Mystics- WomenKingdoms/Factions- Dong Zhuo- Gongsun Du- Gongsun Yuan- Gongsun Zan- Guo Si- Han Fu- Han Sui- Han Xuan- Kong Rong- Li Jue- Liu Biao- Liu Yao (Yong)- Liu Yu- Liu Zhang- Lü Bu- Ma Chao- Ma Teng- Shi Xie- Tao Qian- Tribe: Qiang- Tribe: Nanman- Tribe: Wuhuan- Tribe: Xianbei- Tribe: Xiongnu- Yellow Scarves- Yuan Shang- Yuan Shao- Yuan Shu- Yuan Tan- Zhang Lu- Zhang Yang- Zhang Xiu- Zhao Fan- Zhuge DanforSearch\n“Search” to browse selected faction. Search terms optional.\nSearchthroughover three-thousandofficers using the tools above.\nZe Rong笮融\nLivedAD?–195\nAffiliations\nTao Qian\nZhao Yu\nXue Li\nLiu Yao\nShort Biography\nBuddhist, fought against Sun Ce, had a record of betrayal and murder.\nDetails\nTraditional Chinese笮融\nSimplified Chinese笮融\nWade-GilesTsê Jung\nBirthplaceDanyang\nOther NamesZhai Rong\nName NotesAlso referred to as Zhai Rong in Generals of the South. As well as To Establish Peace.\nRank and Titles\nChancellor of Xiapi\nLiterary Appearances\nRomance of the Three Kingdoms:15\nPremium External Linkage\nZe Rong’s biographyWithin Liu Yao’s SGZ",
  "crawled_at": "2026-03-18T10:05:29.218Z",
  "char_count": 1718
}